surfq/__init__.py
surfq/lattice.py
surfq/lattice_view.py
surfq/pauli.py
surfq/plotting.py
surfq/fonts/Roboto-Regular.ttf
surfq-0.1.3.dist-info/licenses/LICENSE
surfq-0.1.3.dist-info/METADATA
surfq-0.1.3.dist-info/WHEEL
surfq-0.1.3.dist-info/top_level.txt
surfq-0.1.3.dist-info/RECORD
