Metadata-Version: 2.4
Name: surfq
Version: 0.1.3
Summary: A surface code simulator
Author-email: João Ramos <1joaoramos1@gmail.com>
License-Expression: MIT
Keywords: python,project,surfq
Requires-Python: >=3.13
License-File: LICENSE
Requires-Dist: matplotlib>=3.10.5
Requires-Dist: networkx>=3.5
Requires-Dist: numpy>=2.3.2
Requires-Dist: pyqt6>=6.9.1
Requires-Dist: seaborn>=0.13.2
Dynamic: license-file
